pydoom/__init__.py
pydoom-1.0.dist-info/METADATA
pydoom-1.0.dist-info/WHEEL
pydoom-1.0.dist-info/top_level.txt
pydoom-1.0.dist-info/RECORD
