Metadata-Version: 2.4
Name: PyDoom
Version: 1.0
Summary: Create easy doom-like game on python
Requires-Python: >=3.8
Requires-Dist: pygame>=2.0.0
Dynamic: requires-dist
Dynamic: requires-python
Dynamic: summary
